{
  "Title": "Crawl",
  "Media Type": "Movie",
  "Rating": "R",
  "Genre": [
    "Action & Adventure",
    "Horror",
    "Thriller"
  ],
  "Providers": [
    {
      "Prime Video": "https://www.amazon.com/gp/video/detail/amzn1.dv.gti.bcb7fbf9-a54a-48bf-07e4-2bc5df864f91/audiodescriin-20"
    },
    {
      "Apple TV Store": "https://itunes.apple.com/us/movie/id1468540627"
    },
    {
      "DVD": "https://www.amazon.com/dp/B07TPYX1VH/audiodescriin-20"
    },
    {
      "Paramount+": "https://www.paramountplus.com/movies/video/T1yPZs280VlkS2iCYeS5TCyx8eRRZZhd/"
    }
  ],
  "in_theaters": false
}